MANIFEST.in
README.md
setup.py
Reaktor.egg-info/PKG-INFO
Reaktor.egg-info/SOURCES.txt
Reaktor.egg-info/dependency_links.txt
Reaktor.egg-info/entry_points.txt
Reaktor.egg-info/requires.txt
Reaktor.egg-info/top_level.txt
reaktor/__init__.py
reaktor/config.py
reaktor/core.py
reaktor/getconf.py
reaktor/ircasy.py
reaktor/translate_colors.py
reaktor/commands/badcommand
reaktor/commands/caps
reaktor/commands/hello
reaktor/commands/identify
reaktor/commands/licht_resolver
reaktor/commands/nag
reaktor/commands/reload
reaktor/commands/respond
reaktor/commands/rev
reaktor/commands/say
reaktor/commands/showPath
reaktor/commands/taken
reaktor/commands/tell-on_join
reaktor/commands/tell-on_privmsg
reaktor/commands/uptime
reaktor/commands/version
reaktor/commands/whatweb
reaktor/commands/whois