Metadata-Version: 1.1
Name: Reaktor
Version: 0.4.3
Summary: an IRC bot based on asyn* libs
Home-page: http://krebsco.de/
Author: krebs
Author-email: spam@krebsco.de
License: WTFPL
Download-URL: https://pypi.python.org/pypi/Reaktor/
Platform: UNKNOWN
Classifier: Intended Audience :: Developers
Classifier: Natural Language :: English
Classifier: Operating System :: POSIX :: Linux
Classifier: Development Status :: 3 - Alpha
Classifier: Programming Language :: Python
Classifier: Programming Language :: Python :: 2.7
Classifier: Programming Language :: Python :: 3
Classifier: Programming Language :: Python :: 3.4
Classifier: Programming Language :: Python :: Implementation :: CPython
